libinfoblox/__init__.py
libinfoblox-2.2.dist-info/LICENSE
libinfoblox-2.2.dist-info/METADATA
libinfoblox-2.2.dist-info/WHEEL
libinfoblox-2.2.dist-info/top_level.txt
libinfoblox-2.2.dist-info/RECORD
